{
  "_class": "shapePath",
  "booleanOperation": -1,
  "clippingMaskMode": 0,
  "do_objectID": "FA5423D0-A7C3-45A3-9ECB-042C7E59895B",
  "edited": true,
  "exportOptions": {
    "_class": "exportOptions",
    "exportFormats": [
    ],
    "includedLayerIds": [
    ],
    "layerOptions": 0,
    "shouldTrim": false
  },
  "frame": {
    "_class": "rect",
    "constrainProportions": false,
    "height": 3.337241064340214,
    "width": 4.097173209318145,
    "x": 10.08889550403226,
    "y": 12.14504219758065
  },
  "hasClippingMask": false,
  "isClosed": true,
  "isFixedToViewport": false,
  "isFlippedHorizontal": false,
  "isFlippedVertical": false,
  "isLocked": false,
  "isVisible": true,
  "layerListExpandedType": 1,
  "name": "Shape-path",
  "nameIsFixed": false,
  "pointRadiusBehaviour": 1,
  "points": [
    {
      "_class": "curvePoint",
      "cornerRadius": 0,
      "curveFrom": "{0.89018566522305864, 1.2002450223350458}",
      "curveMode": 3,
      "curveTo": "{1.0933883098069248, 0.19896745427416235}",
      "hasCurveFrom": true,
      "hasCurveTo": true,
      "point": "{0.98954808402358885, 0.71011523594414816}"
    },
    {
      "_class": "curvePoint",
      "cornerRadius": 0,
      "curveFrom": "{0, 0.86884534107808076}",
      "curveMode": 4,
      "curveTo": "{0.21794750768292209, 0.93527903216036334}",
      "hasCurveFrom": false,
      "hasCurveTo": true,
      "point": "{0, 0.86884534107808076}"
    },
    {
      "_class": "curvePoint",
      "cornerRadius": 0,
      "curveFrom": "{0.3944959766646482, 0.066767310054966111}",
      "curveMode": 4,
      "curveTo": "{0.17656028377587601, 0}",
      "hasCurveFrom": true,
      "hasCurveTo": false,
      "point": "{0.17656028377587601, 0}"
    }
  ],
  "resizingConstraint": 63,
  "resizingType": 0,
  "rotation": 0,
  "shouldBreakMaskChain": false,
  "style": {
    "_class": "style",
    "blur": {
      "_class": "blur",
      "center": "{0.5, 0.5}",
      "isEnabled": false,
      "motionAngle": 0,
      "radius": 10,
      "saturation": 1,
      "type": 0
    },
    "borderOptions": {
      "_class": "borderOptions",
      "dashPattern": [
      ],
      "isEnabled": true,
      "lineCapStyle": 0,
      "lineJoinStyle": 0
    },
    "borders": [
    ],
    "colorControls": {
      "_class": "colorControls",
      "brightness": 0,
      "contrast": 1,
      "hue": 0,
      "isEnabled": false,
      "saturation": 1
    },
    "contextSettings": {
      "_class": "graphicsContextSettings",
      "blendMode": 0,
      "opacity": 1
    },
    "do_objectID": "056E337E-DB75-4CBC-9900-2CB4A06AFB3A",
    "endMarkerType": 0,
    "fills": [
    ],
    "innerShadows": [
    ],
    "miterLimit": 10,
    "shadows": [
    ],
    "startMarkerType": 0,
    "windingRule": 1
  }
}