{
  "_class": "shapePath",
  "booleanOperation": -1,
  "clippingMaskMode": 0,
  "do_objectID": "4F256867-B66F-4789-8704-0B66554D27DB",
  "edited": true,
  "exportOptions": {
    "_class": "exportOptions",
    "exportFormats": [
    ],
    "includedLayerIds": [
    ],
    "layerOptions": 0,
    "shouldTrim": false
  },
  "frame": {
    "_class": "rect",
    "constrainProportions": false,
    "height": 4.491075434250813,
    "width": 9.73101077451783,
    "x": 11.97660823703704,
    "y": 19.46203209219646
  },
  "hasClippingMask": false,
  "isClosed": true,
  "isFixedToViewport": false,
  "isFlippedHorizontal": false,
  "isFlippedVertical": false,
  "isLocked": false,
  "isVisible": true,
  "layerListExpandedType": 1,
  "name": "Path",
  "nameIsFixed": false,
  "pointRadiusBehaviour": 1,
  "points": [
    {
      "_class": "curvePoint",
      "cornerRadius": 0,
      "curveFrom": "{0.97860410165809031, 0.0003027786521099418}",
      "curveMode": 1,
      "curveTo": "{0.97860410165809031, 0.0003027786521099418}",
      "hasCurveFrom": false,
      "hasCurveTo": false,
      "point": "{0.97860410165809031, 0.0003027786521099418}"
    },
    {
      "_class": "curvePoint",
      "cornerRadius": 0,
      "curveFrom": "{0, 0.23249817085951069}",
      "curveMode": 1,
      "curveTo": "{0, 0.23249817085951069}",
      "hasCurveFrom": false,
      "hasCurveTo": false,
      "point": "{0, 0.23249817085951069}"
    },
    {
      "_class": "curvePoint",
      "cornerRadius": 0,
      "curveFrom": "{0, 0.97741932369716034}",
      "curveMode": 4,
      "curveTo": "{0, 0.91658392259840693}",
      "hasCurveFrom": true,
      "hasCurveTo": false,
      "point": "{0, 0.91658392259840693}"
    },
    {
      "_class": "curvePoint",
      "cornerRadius": 0,
      "curveFrom": "{0.054567214708029228, 0.99221149314240542}",
      "curveMode": 4,
      "curveTo": "{0.029086488897231436, 1.0177331939458214}",
      "hasCurveFrom": false,
      "hasCurveTo": true,
      "point": "{0.054567214708029228, 0.99221149314240542}"
    },
    {
      "_class": "curvePoint",
      "cornerRadius": 0,
      "curveFrom": "{1.0085559736960659, 0.058533924566841949}",
      "curveMode": 4,
      "curveTo": "{0.98918100671162923, 0.079055455416935511}",
      "hasCurveFrom": true,
      "hasCurveTo": false,
      "point": "{0.98918100671162923, 0.079055455416935511}"
    },
    {
      "_class": "curvePoint",
      "cornerRadius": 0,
      "curveFrom": "{0.97860410165809053, 0.00030277865211053394}",
      "curveMode": 4,
      "curveTo": "{0.99999829597093015, -0.0049057317159334445}",
      "hasCurveFrom": false,
      "hasCurveTo": true,
      "point": "{0.97860410165809053, 0.00030277865211053394}"
    }
  ],
  "resizingConstraint": 63,
  "resizingType": 0,
  "rotation": 0,
  "shouldBreakMaskChain": false,
  "style": {
    "_class": "style",
    "blur": {
      "_class": "blur",
      "center": "{0.5, 0.5}",
      "isEnabled": false,
      "motionAngle": 0,
      "radius": 10,
      "saturation": 1,
      "type": 0
    },
    "borderOptions": {
      "_class": "borderOptions",
      "dashPattern": [
      ],
      "isEnabled": true,
      "lineCapStyle": 0,
      "lineJoinStyle": 0
    },
    "borders": [
    ],
    "colorControls": {
      "_class": "colorControls",
      "brightness": 0,
      "contrast": 1,
      "hue": 0,
      "isEnabled": false,
      "saturation": 1
    },
    "contextSettings": {
      "_class": "graphicsContextSettings",
      "blendMode": 0,
      "opacity": 1
    },
    "do_objectID": "87B2DD07-D93F-4772-A33A-4A23BE2FD9F6",
    "endMarkerType": 0,
    "fills": [
    ],
    "innerShadows": [
    ],
    "miterLimit": 10,
    "shadows": [
    ],
    "startMarkerType": 0,
    "windingRule": 1
  }
}