{
  "_class": "shapePath",
  "booleanOperation": -1,
  "clippingMaskMode": 0,
  "do_objectID": "32243A73-66DD-44C1-A41C-0C222A406F34",
  "edited": true,
  "exportOptions": {
    "_class": "exportOptions",
    "exportFormats": [
    ],
    "includedLayerIds": [
    ],
    "layerOptions": 0,
    "shouldTrim": false
  },
  "frame": {
    "_class": "rect",
    "constrainProportions": false,
    "height": 7.084712447699742,
    "width": 9.67425185032086,
    "x": 7.508611952939251,
    "y": 0.2150965084648835
  },
  "hasClippingMask": false,
  "isClosed": true,
  "isFixedToViewport": false,
  "isFlippedHorizontal": false,
  "isFlippedVertical": false,
  "isLocked": false,
  "isVisible": true,
  "layerListExpandedType": 1,
  "name": "Shape-path",
  "nameIsFixed": false,
  "pointRadiusBehaviour": 1,
  "points": [
    {
      "_class": "curvePoint",
      "cornerRadius": 0,
      "curveFrom": "{0.21911884698008807, 1.0026672300291073}",
      "curveMode": 4,
      "curveTo": "{0.24955146306935563, 0.99886056730799888}",
      "hasCurveFrom": true,
      "hasCurveTo": false,
      "point": "{0.24955146306935563, 0.99886056730799888}"
    },
    {
      "_class": "curvePoint",
      "cornerRadius": 0,
      "curveFrom": "{0.20045660657929038, 0.94403405006092522}",
      "curveMode": 4,
      "curveTo": "{0.20494793414462753, 0.97316559394051794}",
      "hasCurveFrom": false,
      "hasCurveTo": true,
      "point": "{0.20045660657929038, 0.94403405006092522}"
    },
    {
      "_class": "curvePoint",
      "cornerRadius": 0,
      "curveFrom": "{0.0038835889136274865, 0.058826356456531545}",
      "curveMode": 4,
      "curveTo": "{0.0076392679984353031, 0.073524304185255282}",
      "hasCurveFrom": true,
      "hasCurveTo": false,
      "point": "{0.0076392679984353031, 0.073524304185255282}"
    },
    {
      "_class": "curvePoint",
      "cornerRadius": 0,
      "curveFrom": "{-0.0012756842410257309, 0.014862939263323598}",
      "curveMode": 4,
      "curveTo": "{0.0014056150844758775, 0.043652575887669291}",
      "hasCurveFrom": true,
      "hasCurveTo": true,
      "point": "{0.00020534651098058575, 0.028161573425381326}"
    },
    {
      "_class": "curvePoint",
      "cornerRadius": 0,
      "curveFrom": "{0.016079866353982803, 0.00019317648834947038}",
      "curveMode": 4,
      "curveTo": "{0.005413153106178255, 0.0024401900663850022}",
      "hasCurveFrom": true,
      "hasCurveTo": true,
      "point": "{0.015150626168050936, 0.00040465775063326529}"
    },
    {
      "_class": "curvePoint",
      "cornerRadius": 0,
      "curveFrom": "{0.13529363854082072, -0.0042479300196102184}",
      "curveMode": 4,
      "curveTo": "{0.0069036195179059444, 0.00040465775063326529}",
      "hasCurveFrom": true,
      "hasCurveTo": true,
      "point": "{0.10129893507214785, 0.00040465775063326529}"
    },
    {
      "_class": "curvePoint",
      "cornerRadius": 0,
      "curveFrom": "{0.14989045312816651, 0.055231174997707036}",
      "curveMode": 4,
      "curveTo": "{0.14636708408984164, 0.032285458039915331}",
      "hasCurveFrom": false,
      "hasCurveTo": true,
      "point": "{0.14989045312816651, 0.055231174997707036}"
    },
    {
      "_class": "curvePoint",
      "cornerRadius": 0,
      "curveFrom": "{0.2881923674676875, 0.79980382918337722}",
      "curveMode": 1,
      "curveTo": "{0.2881923674676875, 0.79980382918337722}",
      "hasCurveFrom": false,
      "hasCurveTo": false,
      "point": "{0.2881923674676875, 0.79980382918337722}"
    },
    {
      "_class": "curvePoint",
      "cornerRadius": 0,
      "curveFrom": "{0.41863445856786841, 0.03820693338386158}",
      "curveMode": 4,
      "curveTo": "{0.41658238649060236, 0.055231174997707036}",
      "hasCurveFrom": true,
      "hasCurveTo": false,
      "point": "{0.41658238649060236, 0.055231174997707036}"
    },
    {
      "_class": "curvePoint",
      "cornerRadius": 0,
      "curveFrom": "{0.46614186307363342, 0.0010919718530556022}",
      "curveMode": 4,
      "curveTo": "{0.4279655787682673, -0.0032962643393331385}",
      "hasCurveFrom": false,
      "hasCurveTo": true,
      "point": "{0.46614186307363342, 0.0010919718530556022}"
    },
    {
      "_class": "curvePoint",
      "cornerRadius": 0,
      "curveFrom": "{0.54098441638222639, 0.00014030617277852283}",
      "curveMode": 4,
      "curveTo": "{0.53258253636775932, 0.0010919718530556022}",
      "hasCurveFrom": true,
      "hasCurveTo": false,
      "point": "{0.53258253636775932, 0.0010919718530556022}"
    },
    {
      "_class": "curvePoint",
      "cornerRadius": 0,
      "curveFrom": "{0.58167739285782449, 0.055918489100129386}",
      "curveMode": 4,
      "curveTo": "{0.57559861330818707, -0.0015515439254918317}",
      "hasCurveFrom": false,
      "hasCurveTo": true,
      "point": "{0.58167739285782449, 0.055918489100129386}"
    },
    {
      "_class": "curvePoint",
      "cornerRadius": 0,
      "curveFrom": "{0.71107408874883216, 0.81000780008857021}",
      "curveMode": 1,
      "curveTo": "{0.71107408874883216, 0.81000780008857021}",
      "hasCurveFrom": false,
      "hasCurveTo": false,
      "point": "{0.71107408874883216, 0.81000780008857021}"
    },
    {
      "_class": "curvePoint",
      "cornerRadius": 0,
      "curveFrom": "{0.85568709268447329, 0.044392760305662575}",
      "curveMode": 4,
      "curveTo": "{0.85382861231260987, 0.055918489100129386}",
      "hasCurveFrom": true,
      "hasCurveTo": false,
      "point": "{0.85382861231260987, 0.055918489100129386}"
    },
    {
      "_class": "curvePoint",
      "cornerRadius": 0,
      "curveFrom": "{0.90292346880267493, 0.0010919718530556022}",
      "curveMode": 4,
      "curveTo": "{0.86436000108650379, -0.0041950597040392654}",
      "hasCurveFrom": false,
      "hasCurveTo": true,
      "point": "{0.90292346880267493, 0.0010919718530556022}"
    },
    {
      "_class": "curvePoint",
      "cornerRadius": 0,
      "curveFrom": "{0.98256709640524909, 0.00040465775063326529}",
      "curveMode": 4,
      "curveTo": "{0.97927603741340707, 0.0010919718530556022}",
      "hasCurveFrom": true,
      "hasCurveTo": false,
      "point": "{0.97927603741340707, 0.0010919718530556022}"
    },
    {
      "_class": "curvePoint",
      "cornerRadius": 0,
      "curveFrom": "{0.99793827781420452, 0.056235710993555073}",
      "curveMode": 4,
      "curveTo": "{1.0030878171779103, -0.0031905237081912433}",
      "hasCurveFrom": true,
      "hasCurveTo": true,
      "point": "{0.99960316648066594, 0.046454702612929576}"
    },
    {
      "_class": "curvePoint",
      "cornerRadius": 0,
      "curveFrom": "{0.79091130805680865, 0.97385290804294022}",
      "curveMode": 4,
      "curveTo": "{1.0128061207891139, -0.0099050537857017229}",
      "hasCurveFrom": true,
      "hasCurveTo": true,
      "point": "{0.79536391728106526, 0.94472136416334762}"
    },
    {
      "_class": "curvePoint",
      "cornerRadius": 0,
      "curveFrom": "{0.74626906079100019, 0.99954788141042139}",
      "curveMode": 4,
      "curveTo": "{0.7767016768802677, 1.0033545441315297}",
      "hasCurveFrom": false,
      "hasCurveTo": true,
      "point": "{0.74626906079100019, 0.99954788141042139}"
    },
    {
      "_class": "curvePoint",
      "cornerRadius": 0,
      "curveFrom": "{0.63154661616949948, 1.0056279677010804}",
      "curveMode": 4,
      "curveTo": "{0.67390448131155878, 0.99954788141042139}",
      "hasCurveFrom": true,
      "hasCurveTo": false,
      "point": "{0.67390448131155878, 0.99954788141042139}"
    },
    {
      "_class": "curvePoint",
      "cornerRadius": 0,
      "curveFrom": "{0.6248096248214936, 0.94271229217165153}",
      "curveMode": 4,
      "curveTo": "{0.62546783661986205, 0.94847515656888481}",
      "hasCurveFrom": false,
      "hasCurveTo": true,
      "point": "{0.6248096248214936, 0.94271229217165153}"
    },
    {
      "_class": "curvePoint",
      "cornerRadius": 0,
      "curveFrom": "{0.49641960579857897, 0.21770165474723235}",
      "curveMode": 1,
      "curveTo": "{0.49641960579857897, 0.21770165474723235}",
      "hasCurveFrom": false,
      "hasCurveTo": false,
      "point": "{0.49641960579857897, 0.21770165474723235}"
    },
    {
      "_class": "curvePoint",
      "cornerRadius": 0,
      "curveFrom": "{0.36888139027943501, 0.94773497215089164}",
      "curveMode": 4,
      "curveTo": "{0.3695008837367228, 0.94197210775365825}",
      "hasCurveFrom": true,
      "hasCurveTo": false,
      "point": "{0.3695008837367228, 0.94197210775365825}"
    },
    {
      "_class": "curvePoint",
      "cornerRadius": 0,
      "curveFrom": "{0.32040602724665762, 0.998807696992428}",
      "curveMode": 4,
      "curveTo": "{0.36280261072979764, 1.0048877832830871}",
      "hasCurveFrom": false,
      "hasCurveTo": true,
      "point": "{0.32040602724665762, 0.998807696992428}"
    },
    {
      "_class": "curvePoint",
      "cornerRadius": 0,
      "curveFrom": "{0.24955146306935563, 0.998807696992428}",
      "curveMode": 1,
      "curveTo": "{0.24955146306935563, 0.998807696992428}",
      "hasCurveFrom": false,
      "hasCurveTo": false,
      "point": "{0.24955146306935563, 0.998807696992428}"
    }
  ],
  "resizingConstraint": 63,
  "resizingType": 0,
  "rotation": 0,
  "shouldBreakMaskChain": false,
  "style": {
    "_class": "style",
    "blur": {
      "_class": "blur",
      "center": "{0.5, 0.5}",
      "isEnabled": false,
      "motionAngle": 0,
      "radius": 10,
      "saturation": 1,
      "type": 0
    },
    "borderOptions": {
      "_class": "borderOptions",
      "dashPattern": [
      ],
      "isEnabled": true,
      "lineCapStyle": 0,
      "lineJoinStyle": 0
    },
    "borders": [
    ],
    "colorControls": {
      "_class": "colorControls",
      "brightness": 0,
      "contrast": 1,
      "hue": 0,
      "isEnabled": false,
      "saturation": 1
    },
    "contextSettings": {
      "_class": "graphicsContextSettings",
      "blendMode": 0,
      "opacity": 1
    },
    "do_objectID": "6DD80EAF-05C0-4B2F-9A2A-D33B531B8046",
    "endMarkerType": 0,
    "fills": [
    ],
    "innerShadows": [
    ],
    "miterLimit": 10,
    "shadows": [
    ],
    "startMarkerType": 0,
    "windingRule": 1
  }
}