{
  "_class": "group",
  "booleanOperation": -1,
  "clippingMaskMode": 0,
  "do_objectID": "8FFF9812-D13F-464A-B507-07B6C3483C22",
  "exportOptions": {
    "_class": "exportOptions",
    "exportFormats": [
    ],
    "includedLayerIds": [
    ],
    "layerOptions": 0,
    "shouldTrim": false
  },
  "frame": {
    "_class": "rect",
    "constrainProportions": false,
    "height": 50,
    "width": 908,
    "x": 756,
    "y": 2066.56699583455
  },
  "groupLayout": {
    "_class": "MSImmutableFreeformGroupLayout"
  },
  "hasClickThrough": false,
  "hasClippingMask": false,
  "isFixedToViewport": false,
  "isFlippedHorizontal": false,
  "isFlippedVertical": false,
  "isLocked": false,
  "isVisible": true,
  "layerListExpandedType": 1,
  "layers": [
    {
      "class": "group",
      "id": "7B9F8A6D-A9DD-4357-95C4-2D305DE37B10"
    },
    {
      "class": "group",
      "id": "CA147129-0BE0-4222-A458-AB075EECD4F4"
    },
    {
      "class": "group",
      "id": "C9B1EDBC-8142-4B66-BE12-15B17822AF52"
    },
    {
      "class": "group",
      "id": "25A07964-5A4F-43A0-8A6D-4B811709536D"
    },
    {
      "class": "group",
      "id": "9E7F890F-528A-4E1F-B078-52DBB2A3C929"
    },
    {
      "class": "group",
      "id": "BB411DE1-4EDA-480E-A1E6-575095028F19"
    },
    {
      "class": "group",
      "id": "A4E1D960-63A8-4B37-A116-E59B56960314"
    },
    {
      "class": "group",
      "id": "8354E970-9348-4E7E-B5BC-622D7A9455E7"
    },
    {
      "class": "group",
      "id": "10314D72-0EE9-41EF-AD55-2284081F0E95"
    },
    {
      "class": "group",
      "id": "643F9227-F756-4DC0-91B7-B637BC2668C0"
    },
    {
      "class": "text",
      "id": "76CB317D-216E-488E-8461-429B88380DBE"
    }
  ],
  "name": "red-cool",
  "nameIsFixed": true,
  "resizingConstraint": 63,
  "resizingType": 0,
  "rotation": 0,
  "shouldBreakMaskChain": false,
  "style": {
    "_class": "style",
    "blur": {
      "_class": "blur",
      "center": "{0.5, 0.5}",
      "isEnabled": false,
      "motionAngle": 0,
      "radius": 10,
      "saturation": 1,
      "type": 0
    },
    "borderOptions": {
      "_class": "borderOptions",
      "dashPattern": [
      ],
      "isEnabled": true,
      "lineCapStyle": 0,
      "lineJoinStyle": 0
    },
    "borders": [
    ],
    "colorControls": {
      "_class": "colorControls",
      "brightness": 0,
      "contrast": 1,
      "hue": 0,
      "isEnabled": false,
      "saturation": 1
    },
    "contextSettings": {
      "_class": "graphicsContextSettings",
      "blendMode": 0,
      "opacity": 1
    },
    "do_objectID": "EFC2C8BD-EFA5-48DC-B6CD-0E848CE91C61",
    "endMarkerType": 0,
    "fills": [
    ],
    "innerShadows": [
    ],
    "miterLimit": 10,
    "shadows": [
    ],
    "startMarkerType": 0,
    "windingRule": 1
  }
}