{
  "_class": "shapePath",
  "booleanOperation": -1,
  "clippingMaskMode": 0,
  "do_objectID": "7B009494-5839-4D91-BD00-DF7465256F19",
  "edited": true,
  "exportOptions": {
    "_class": "exportOptions",
    "exportFormats": [
    ],
    "includedLayerIds": [
    ],
    "layerOptions": 0,
    "shouldTrim": false
  },
  "frame": {
    "_class": "rect",
    "constrainProportions": false,
    "height": 14.6250000609375,
    "width": 23.98832046750622,
    "x": 0.004667941242005931,
    "y": 7.50468753126953
  },
  "hasClippingMask": false,
  "isClosed": true,
  "isFixedToViewport": false,
  "isFlippedHorizontal": false,
  "isFlippedVertical": false,
  "isLocked": false,
  "isVisible": true,
  "layerListExpandedType": 1,
  "name": "Path",
  "nameIsFixed": false,
  "pointRadiusBehaviour": 1,
  "points": [
    {
      "_class": "curvePoint",
      "cornerRadius": 0,
      "curveFrom": "{0.66687336344875581, 0}",
      "curveMode": 4,
      "curveTo": "{0.67982383963966087, 0}",
      "hasCurveFrom": true,
      "hasCurveTo": false,
      "point": "{0.67982383963966087, 0}"
    },
    {
      "_class": "curvePoint",
      "cornerRadius": 0,
      "curveFrom": "{0.65637492819520626, 0.038461538461538464}",
      "curveMode": 4,
      "curveTo": "{0.65637492819520626, 0.017219817314200307}",
      "hasCurveFrom": false,
      "hasCurveTo": true,
      "point": "{0.65637492819520626, 0.038461538461538464}"
    },
    {
      "_class": "curvePoint",
      "cornerRadius": 0,
      "curveFrom": "{0.65637492819520626, 0.61570512820512824}",
      "curveMode": 4,
      "curveTo": "{0.65637492819520626, 0.20512820512820512}",
      "hasCurveFrom": true,
      "hasCurveTo": false,
      "point": "{0.65637492819520626, 0.20512820512820512}"
    },
    {
      "_class": "curvePoint",
      "cornerRadius": 0,
      "curveFrom": "{0.34372277560247888, 0.20512820512820512}",
      "curveMode": 4,
      "curveTo": "{0.34372277560247888, 0.6150641025641026}",
      "hasCurveFrom": false,
      "hasCurveTo": true,
      "point": "{0.34372277560247888, 0.20512820512820512}"
    },
    {
      "_class": "curvePoint",
      "cornerRadius": 0,
      "curveFrom": "{0.34372277560247888, 0.017219817314200307}",
      "curveMode": 4,
      "curveTo": "{0.34372277560247888, 0.038461538461538464}",
      "hasCurveFrom": true,
      "hasCurveTo": false,
      "point": "{0.34372277560247888, 0.038461538461538464}"
    },
    {
      "_class": "curvePoint",
      "cornerRadius": 0,
      "curveFrom": "{0.32027386415802434, 0}",
      "curveMode": 4,
      "curveTo": "{0.33322434034892934, 0}",
      "hasCurveFrom": false,
      "hasCurveTo": true,
      "point": "{0.32027386415802434, 0}"
    },
    {
      "_class": "curvePoint",
      "cornerRadius": 0,
      "curveFrom": "{0.017196683737277445, -3.5613159090676396e-07}",
      "curveMode": 4,
      "curveTo": "{0.023449726790303868, 0}",
      "hasCurveFrom": true,
      "hasCurveTo": false,
      "point": "{0.023449726790303868, 0}"
    },
    {
      "_class": "curvePoint",
      "cornerRadius": 0,
      "curveFrom": "{0.0023961867807231131, 0.01866061253011763}",
      "curveMode": 2,
      "curveTo": "{0.011202555747068847, 0.0040957977125729373}",
      "hasCurveFrom": true,
      "hasCurveTo": true,
      "point": "{0.00679937126389598, 0.011378205121345238}"
    },
    {
      "_class": "curvePoint",
      "cornerRadius": 0,
      "curveFrom": "{0.00019622294121977041, 0.10737179487179487}",
      "curveMode": 3,
      "curveTo": "{-5.1293350060221673e-05, 0.028525997149126844}",
      "hasCurveFrom": true,
      "hasCurveTo": true,
      "point": "{8.1534584931582654e-07, 0.038782051282051262}"
    },
    {
      "_class": "curvePoint",
      "cornerRadius": 0,
      "curveFrom": "{8.1534584931582654e-07, 0.6923076923076924}",
      "curveMode": 4,
      "curveTo": "{0.0011732609180720433, 0.16794871794871796}",
      "hasCurveFrom": true,
      "hasCurveTo": true,
      "point": "{8.1534584931582654e-07, 0.20961538461538462}"
    },
    {
      "_class": "curvePoint",
      "cornerRadius": 0,
      "curveFrom": "{0.73733229495718577, 1}",
      "curveMode": 2,
      "curveTo": "{0.26608733796179729, 1}",
      "hasCurveFrom": true,
      "hasCurveTo": true,
      "point": "{0.50170981645949153, 1}"
    },
    {
      "_class": "curvePoint",
      "cornerRadius": 0,
      "curveFrom": "{0.99882673908192798, 0.16826923076923087}",
      "curveMode": 4,
      "curveTo": "{0.99999918465415072, 0.6923076923076924}",
      "hasCurveFrom": true,
      "hasCurveTo": true,
      "point": "{0.99999918465415072, 0.20929487179487191}"
    },
    {
      "_class": "curvePoint",
      "cornerRadius": 0,
      "curveFrom": "{1.0000512933500603, 0.028525997149126934}",
      "curveMode": 3,
      "curveTo": "{0.99960836946340981, 0.10352564102564116}",
      "hasCurveFrom": true,
      "hasCurveTo": true,
      "point": "{0.99999918465415072, 0.038782051282051443}"
    },
    {
      "_class": "curvePoint",
      "cornerRadius": 0,
      "curveFrom": "{0.98879744425293126, 0.0040957977125730283}",
      "curveMode": 2,
      "curveTo": "{0.99760381321927705, 0.018660612530117814}",
      "hasCurveFrom": true,
      "hasCurveTo": true,
      "point": "{0.99320062873610415, 0.01137820512134542}"
    },
    {
      "_class": "curvePoint",
      "cornerRadius": 0,
      "curveFrom": "{0.97655027320969612, 9.1095222533346175e-17}",
      "curveMode": 4,
      "curveTo": "{0.98280331626272266, -3.5613159081566874e-07}",
      "hasCurveFrom": false,
      "hasCurveTo": true,
      "point": "{0.97655027320969612, 9.1095222533346175e-17}"
    }
  ],
  "resizingConstraint": 63,
  "resizingType": 0,
  "rotation": 0,
  "shouldBreakMaskChain": false,
  "style": {
    "_class": "style",
    "blur": {
      "_class": "blur",
      "center": "{0.5, 0.5}",
      "isEnabled": false,
      "motionAngle": 0,
      "radius": 10,
      "saturation": 1,
      "type": 0
    },
    "borderOptions": {
      "_class": "borderOptions",
      "dashPattern": [
      ],
      "isEnabled": true,
      "lineCapStyle": 0,
      "lineJoinStyle": 0
    },
    "borders": [
    ],
    "colorControls": {
      "_class": "colorControls",
      "brightness": 0,
      "contrast": 1,
      "hue": 0,
      "isEnabled": false,
      "saturation": 1
    },
    "contextSettings": {
      "_class": "graphicsContextSettings",
      "blendMode": 0,
      "opacity": 1
    },
    "do_objectID": "F50B5C37-8F1A-4E53-93C9-396F5ADB177F",
    "endMarkerType": 0,
    "fills": [
    ],
    "innerShadows": [
    ],
    "miterLimit": 10,
    "shadows": [
    ],
    "startMarkerType": 0,
    "windingRule": 1
  }
}