{
  "_class": "shapePath",
  "booleanOperation": -1,
  "clippingMaskMode": 0,
  "do_objectID": "11005247-8784-4C55-8A03-149129847DCE",
  "edited": true,
  "exportOptions": {
    "_class": "exportOptions",
    "exportFormats": [
    ],
    "includedLayerIds": [
    ],
    "layerOptions": 0,
    "shouldTrim": false
  },
  "frame": {
    "_class": "rect",
    "constrainProportions": false,
    "height": 24.00000835153672,
    "width": 23.99999860426682,
    "x": 0,
    "y": 0.000008172933848857886
  },
  "hasClippingMask": false,
  "isClosed": true,
  "isFixedToViewport": false,
  "isFlippedHorizontal": false,
  "isFlippedVertical": false,
  "isLocked": false,
  "isVisible": true,
  "layerListExpandedType": 1,
  "name": "Path",
  "nameIsFixed": false,
  "pointRadiusBehaviour": 1,
  "points": [
    {
      "_class": "curvePoint",
      "cornerRadius": 0,
      "curveFrom": "{0.98165958368741479, 0.60555103506862307}",
      "curveMode": 4,
      "curveTo": "{0.9933611705187938, 0.59393168282939768}",
      "hasCurveFrom": false,
      "hasCurveTo": true,
      "point": "{0.98165958368741479, 0.60555103506862307}"
    },
    {
      "_class": "curvePoint",
      "cornerRadius": 0,
      "curveFrom": "{0.768485209138277, 0.81866379730584493}",
      "curveMode": 4,
      "curveTo": "{0.79278470863506412, 0.79444989590379478}",
      "hasCurveFrom": true,
      "hasCurveTo": false,
      "point": "{0.79278470863506412, 0.79444989590379478}"
    },
    {
      "_class": "curvePoint",
      "cornerRadius": 0,
      "curveFrom": "{0.70487913675034397, 0.79444989590379467}",
      "curveMode": 4,
      "curveTo": "{0.72917863624713097, 0.81866379730584493}",
      "hasCurveFrom": false,
      "hasCurveTo": true,
      "point": "{0.70487913675034397, 0.79444989590379467}"
    },
    {
      "_class": "curvePoint",
      "cornerRadius": 0,
      "curveFrom": "{0.54799219337905225, 0.63738518427984603}",
      "curveMode": 1,
      "curveTo": "{0.54799219337905225, 0.63738518427984603}",
      "hasCurveFrom": false,
      "hasCurveTo": false,
      "point": "{0.54799219337905225, 0.63738518427984603}"
    },
    {
      "_class": "curvePoint",
      "cornerRadius": 0,
      "curveFrom": "{0.57652061758225137, 0.76212522392341908}",
      "curveMode": 4,
      "curveTo": "{0.52867127420617976, 0.65673593934553509}",
      "hasCurveFrom": true,
      "hasCurveTo": false,
      "point": "{0.52867127420617976, 0.65673593934553509}"
    },
    {
      "_class": "curvePoint",
      "cornerRadius": 0,
      "curveFrom": "{0.509319847218906, 1.002485859534362}",
      "curveMode": 3,
      "curveTo": "{0.57261734598326475, 0.88377693482123354}",
      "hasCurveFrom": true,
      "hasCurveTo": true,
      "point": "{0.51811041417300352, 0.98588205664923256}"
    },
    {
      "_class": "curvePoint",
      "cornerRadius": 0,
      "curveFrom": "{0.4727841027544174, 0.99134543367709693}",
      "curveMode": 4,
      "curveTo": "{0.48609201374004585, 1.0046223822372955}",
      "hasCurveFrom": false,
      "hasCurveTo": true,
      "point": "{0.4727841027544174, 0.99134543367709693}"
    },
    {
      "_class": "curvePoint",
      "cornerRadius": 0,
      "curveFrom": "{0.26278739044820693, 0.78135609181187837}",
      "curveMode": 1,
      "curveTo": "{0.26278739044820693, 0.78135609181187837}",
      "hasCurveFrom": false,
      "hasCurveTo": false,
      "point": "{0.26278739044820693, 0.78135609181187837}"
    },
    {
      "_class": "curvePoint",
      "cornerRadius": 0,
      "curveFrom": "{0.22939547430464871, 0.82121742576324241}",
      "curveMode": 4,
      "curveTo": "{0.2280219585940482, 0.81612031814069963}",
      "hasCurveFrom": true,
      "hasCurveTo": false,
      "point": "{0.2280219585940482, 0.81612031814069963}"
    },
    {
      "_class": "curvePoint",
      "cornerRadius": 0,
      "curveFrom": "{0.23116667541485747, 0.85663401944782036}",
      "curveMode": 3,
      "curveTo": "{0.23116580644622975, 0.82588724837644201}",
      "hasCurveFrom": true,
      "hasCurveTo": true,
      "point": "{0.23116580644622975, 0.83135064493554955}"
    },
    {
      "_class": "curvePoint",
      "cornerRadius": 0,
      "curveFrom": "{0.16921989597500053, 0.89878057452975468}",
      "curveMode": 2,
      "curveTo": "{0.21593700059748358, 0.87942831320459558}",
      "hasCurveFrom": true,
      "hasCurveTo": true,
      "point": "{0.19257844828624204, 0.88910444386717502}"
    },
    {
      "_class": "curvePoint",
      "cornerRadius": 0,
      "curveFrom": "{0.10657588753605041, 0.85767748625762785}",
      "curveMode": 2,
      "curveTo": "{0.14233260767571446, 0.89343296294735908}",
      "hasCurveFrom": true,
      "hasCurveTo": true,
      "point": "{0.12445424760588243, 0.87555522460249335}"
    },
    {
      "_class": "curvePoint",
      "cornerRadius": 0,
      "curveFrom": "{0.12057801319391206, 0.78407264193645332}",
      "curveMode": 2,
      "curveTo": "{0.10122734967563471, 0.83079039269018273}",
      "hasCurveFrom": true,
      "hasCurveTo": true,
      "point": "{0.11090268143477339, 0.80743151731331808}"
    },
    {
      "_class": "curvePoint",
      "cornerRadius": 0,
      "curveFrom": "{0.17411875210968089, 0.76884218986433328}",
      "curveMode": 3,
      "curveTo": "{0.14337179275472978, 0.76884218987926622}",
      "hasCurveFrom": true,
      "hasCurveTo": true,
      "point": "{0.16865517755042883, 0.76884218986433328}"
    },
    {
      "_class": "curvePoint",
      "cornerRadius": 0,
      "curveFrom": "{0.18388603787464977, 0.77198591925222515}",
      "curveMode": 4,
      "curveTo": "{0.17878873286947444, 0.77061244316194533}",
      "hasCurveFrom": false,
      "hasCurveTo": true,
      "point": "{0.18388603787464977, 0.77198591925222515}"
    },
    {
      "_class": "curvePoint",
      "cornerRadius": 0,
      "curveFrom": "{0.21865146972880853, 0.73722169292340389}",
      "curveMode": 1,
      "curveTo": "{0.21865146972880853, 0.73722169292340389}",
      "hasCurveFrom": false,
      "hasCurveTo": false,
      "point": "{0.21865146972880853, 0.73722169292340389}"
    },
    {
      "_class": "curvePoint",
      "cornerRadius": 0,
      "curveFrom": "{-0.0046225090298704138, 0.51392487516473229}",
      "curveMode": 4,
      "curveTo": "{0.008654835547603117, 0.52723233152694216}",
      "hasCurveFrom": true,
      "hasCurveTo": false,
      "point": "{0.008654835547603117, 0.52723233152694216}"
    },
    {
      "_class": "curvePoint",
      "cornerRadius": 0,
      "curveFrom": "{0.11622810109578356, 0.42740250524674878}",
      "curveMode": 3,
      "curveTo": "{-0.0024859659279663142, 0.49088097683754789}",
      "hasCurveFrom": true,
      "hasCurveTo": true,
      "point": "{0.014118410106855188, 0.48190760101647034}"
    },
    {
      "_class": "curvePoint",
      "cornerRadius": 0,
      "curveFrom": "{0.34327593062068118, 0.47134705777233316}",
      "curveMode": 4,
      "curveTo": "{0.23788239691607721, 0.42349940301824807}",
      "hasCurveFrom": false,
      "hasCurveTo": true,
      "point": "{0.34327593062068118, 0.47134705777233316}"
    },
    {
      "_class": "curvePoint",
      "cornerRadius": 0,
      "curveFrom": "{0.36241370525088973, 0.45220993544569427}",
      "curveMode": 1,
      "curveTo": "{0.36241370525088973, 0.45220993544569427}",
      "hasCurveFrom": false,
      "hasCurveTo": false,
      "point": "{0.36241370525088973, 0.45220993544569427}"
    },
    {
      "_class": "curvePoint",
      "cornerRadius": 0,
      "curveFrom": "{0.18135264136971219, 0.27077160721744864}",
      "curveMode": 4,
      "curveTo": "{0.20555719156899427, 0.29514522382174552}",
      "hasCurveFrom": true,
      "hasCurveTo": false,
      "point": "{0.20555719156899427, 0.29514522382174552}"
    },
    {
      "_class": "curvePoint",
      "cornerRadius": 0,
      "curveFrom": "{0.20555719156899427, 0.20705957051307883}",
      "curveMode": 4,
      "curveTo": "{0.18135264136971219, 0.23143318711737573}",
      "hasCurveFrom": false,
      "hasCurveTo": true,
      "point": "{0.20555719156899427, 0.20705957051307883}"
    },
    {
      "_class": "curvePoint",
      "cornerRadius": 0,
      "curveFrom": "{0.40610255988754479, 0.0064839602800740971}",
      "curveMode": 4,
      "curveTo": "{0.39446237912323401, 0.018160768271637082}",
      "hasCurveFrom": true,
      "hasCurveTo": false,
      "point": "{0.39446237912323401, 0.018160768271637082}"
    },
    {
      "_class": "curvePoint",
      "cornerRadius": 0,
      "curveFrom": "{0.45495043061427448, -2.2924402168705418e-05}",
      "curveMode": 4,
      "curveTo": "{0.42192785701601315, -5.4706659175794428e-05}",
      "hasCurveFrom": true,
      "hasCurveTo": true,
      "point": "{0.438415389674983, 3.4482794543495397e-07}"
    },
    {
      "_class": "curvePoint",
      "cornerRadius": 0,
      "curveFrom": "{0.48255131039438137, 0.018160768271637092}",
      "curveMode": 4,
      "curveTo": "{0.47082088295691943, 0.0065072245125380066}",
      "hasCurveFrom": false,
      "hasCurveTo": true,
      "point": "{0.48255131039438137, 0.018160768271637092}"
    },
    {
      "_class": "curvePoint",
      "cornerRadius": 0,
      "curveFrom": "{0.63943833189067822, 0.17501182762529249}",
      "curveMode": 1,
      "curveTo": "{0.63943833189067822, 0.17501182762529249}",
      "hasCurveFrom": false,
      "hasCurveTo": false,
      "point": "{0.63943833189067822, 0.17501182762529249}"
    },
    {
      "_class": "curvePoint",
      "cornerRadius": 0,
      "curveFrom": "{0.75843685977043906, 0.055855073145306078}",
      "curveMode": 4,
      "curveTo": "{0.73280747833465032, 0.081462777757518201}",
      "hasCurveFrom": true,
      "hasCurveTo": false,
      "point": "{0.73280747833465032, 0.081462777757518201}"
    },
    {
      "_class": "curvePoint",
      "cornerRadius": 0,
      "curveFrom": "{0.82559670286748033, 0.081462777757518229}",
      "curveMode": 4,
      "curveTo": "{0.79996732143169158, 0.055855073145306078}",
      "hasCurveFrom": false,
      "hasCurveTo": true,
      "point": "{0.82559670286748033, 0.081462777757518229}"
    },
    {
      "_class": "curvePoint",
      "cornerRadius": 0,
      "curveFrom": "{0.94396397545092292, 0.19988916769284149}",
      "curveMode": 4,
      "curveTo": "{0.91838590786905916, 0.17424878101263866}",
      "hasCurveFrom": true,
      "hasCurveTo": false,
      "point": "{0.91838590786905916, 0.17424878101263866}"
    },
    {
      "_class": "curvePoint",
      "cornerRadius": 0,
      "curveFrom": "{0.91838590786905916, 0.26703476473651577}",
      "curveMode": 4,
      "curveTo": "{0.94396397545092292, 0.24139437805631292}",
      "hasCurveFrom": false,
      "hasCurveTo": true,
      "point": "{0.91838590786905916, 0.26703476473651577}"
    },
    {
      "_class": "curvePoint",
      "cornerRadius": 0,
      "curveFrom": "{0.82501676142508706, 0.36058381460429012}",
      "curveMode": 1,
      "curveTo": "{0.82501676142508706, 0.36058381460429012}",
      "hasCurveFrom": false,
      "hasCurveTo": false,
      "point": "{0.82501676142508706, 0.36058381460429012}"
    },
    {
      "_class": "curvePoint",
      "cornerRadius": 0,
      "curveFrom": "{0.9935182018280172, 0.52932470180304514}",
      "curveMode": 4,
      "curveTo": "{0.98187323604448007, 0.51764860435321192}",
      "hasCurveFrom": true,
      "hasCurveTo": false,
      "point": "{0.98187323604448007, 0.51764860435321192}"
    },
    {
      "_class": "curvePoint",
      "cornerRadius": 0,
      "curveFrom": "{0.99995973528252025, 0.57813458171046495}",
      "curveMode": 2,
      "curveTo": "{1.0000398973970206, 0.5451536925096222}",
      "hasCurveFrom": true,
      "hasCurveTo": true,
      "point": "{0.99999981633977042, 0.56164413711004357}"
    }
  ],
  "resizingConstraint": 63,
  "resizingType": 0,
  "rotation": 0,
  "shouldBreakMaskChain": false,
  "style": {
    "_class": "style",
    "blur": {
      "_class": "blur",
      "center": "{0.5, 0.5}",
      "isEnabled": false,
      "motionAngle": 0,
      "radius": 10,
      "saturation": 1,
      "type": 0
    },
    "borderOptions": {
      "_class": "borderOptions",
      "dashPattern": [
      ],
      "isEnabled": true,
      "lineCapStyle": 0,
      "lineJoinStyle": 0
    },
    "borders": [
    ],
    "colorControls": {
      "_class": "colorControls",
      "brightness": 0,
      "contrast": 1,
      "hue": 0,
      "isEnabled": false,
      "saturation": 1
    },
    "contextSettings": {
      "_class": "graphicsContextSettings",
      "blendMode": 0,
      "opacity": 1
    },
    "do_objectID": "8BBD1689-044D-437E-A62F-C19C99E45468",
    "endMarkerType": 0,
    "fills": [
    ],
    "innerShadows": [
    ],
    "miterLimit": 10,
    "shadows": [
    ],
    "startMarkerType": 0,
    "windingRule": 1
  }
}