{
  "_class": "shapePath",
  "booleanOperation": -1,
  "clippingMaskMode": 0,
  "do_objectID": "6990A5B0-0622-4D9A-8407-771A4BFD78A5",
  "edited": true,
  "exportOptions": {
    "_class": "exportOptions",
    "exportFormats": [
    ],
    "includedLayerIds": [
    ],
    "layerOptions": 0,
    "shouldTrim": false
  },
  "frame": {
    "_class": "rect",
    "constrainProportions": false,
    "height": 10.49476313642421,
    "width": 9.601309345158263,
    "x": 7.199416414476282,
    "y": 4.352995513636107
  },
  "hasClippingMask": false,
  "isClosed": true,
  "isFixedToViewport": false,
  "isFlippedHorizontal": false,
  "isFlippedVertical": false,
  "isLocked": false,
  "isVisible": true,
  "layerListExpandedType": 1,
  "name": "Path",
  "nameIsFixed": false,
  "pointRadiusBehaviour": 1,
  "points": [
    {
      "_class": "curvePoint",
      "cornerRadius": 0,
      "curveFrom": "{0.025656227192462005, 0.22566313101304708}",
      "curveMode": 2,
      "curveTo": "{-0.0039421359931599695, 0.27279710355477366}",
      "hasCurveFrom": true,
      "hasCurveTo": true,
      "point": "{0.010879621955854081, 0.24937480545156848}"
    },
    {
      "_class": "curvePoint",
      "cornerRadius": 0,
      "curveFrom": "{0.083057277937427579, 0.21110571862677713}",
      "curveMode": 4,
      "curveTo": "{0.053222806107195632, 0.21104714234448008}",
      "hasCurveFrom": false,
      "hasCurveTo": true,
      "point": "{0.083057277937427579, 0.21110571862677713}"
    },
    {
      "_class": "curvePoint",
      "cornerRadius": 0,
      "curveFrom": "{0.31525217231537933, 0.21110571862677713}",
      "curveMode": 1,
      "curveTo": "{0.31525217231537933, 0.21110571862677713}",
      "hasCurveFrom": false,
      "hasCurveTo": false,
      "point": "{0.31525217231537933, 0.21110571862677713}"
    },
    {
      "_class": "curvePoint",
      "cornerRadius": 0,
      "curveFrom": "{0.44390431962708354, 0.014049431570071375}",
      "curveMode": 4,
      "curveTo": "{0.42902571770191811, 0.037054624393762628}",
      "hasCurveFrom": true,
      "hasCurveTo": false,
      "point": "{0.42902571770191811, 0.037054624393762628}"
    },
    {
      "_class": "curvePoint",
      "cornerRadius": 0,
      "curveFrom": "{0.52897970614606626, -8.8983870311348486e-05}",
      "curveMode": 4,
      "curveTo": "{0.47096992522735548, -4.3649625998646002e-05}",
      "hasCurveFrom": true,
      "hasCurveTo": true,
      "point": "{0.50018788718158624, 4.2921420276474053e-07}"
    },
    {
      "_class": "curvePoint",
      "cornerRadius": 0,
      "curveFrom": "{0.57029551298619929, 0.036482910678359647}",
      "curveMode": 4,
      "curveTo": "{0.55566391392689607, 0.013796896653769569}",
      "hasCurveFrom": false,
      "hasCurveTo": true,
      "point": "{0.57029551298619929, 0.036482910678359647}"
    },
    {
      "_class": "curvePoint",
      "cornerRadius": 0,
      "curveFrom": "{0.6845377444505405, 0.21106998651956446}",
      "curveMode": 1,
      "curveTo": "{0.6845377444505405, 0.21106998651956446}",
      "hasCurveFrom": false,
      "hasCurveTo": false,
      "point": "{0.6845377444505405, 0.21106998651956446}"
    },
    {
      "_class": "curvePoint",
      "cornerRadius": 0,
      "curveFrom": "{0.94673436120225107, 0.21107247645813149}",
      "curveMode": 4,
      "curveTo": "{0.91700603904054356, 0.21106998651956446}",
      "hasCurveFrom": true,
      "hasCurveTo": false,
      "point": "{0.91700603904054356, 0.21106998651956446}"
    },
    {
      "_class": "curvePoint",
      "cornerRadius": 0,
      "curveFrom": "{1.003433616812248, 0.27305516674275027}",
      "curveMode": 2,
      "curveTo": "{0.97416155773744539, 0.22570925352464166}",
      "hasCurveFrom": true,
      "hasCurveTo": true,
      "point": "{0.98879758727484668, 0.24938221013369602}"
    },
    {
      "_class": "curvePoint",
      "cornerRadius": 0,
      "curveFrom": "{0.98769952244240944, 0.32541272960017342}",
      "curveMode": 4,
      "curveTo": "{1.0030141128356886, 0.3021018170987822}",
      "hasCurveFrom": false,
      "hasCurveTo": true,
      "point": "{0.98769952244240944, 0.32541272960017342}"
    },
    {
      "_class": "curvePoint",
      "cornerRadius": 0,
      "curveFrom": "{0.87349634815121846, 0.49996407333416554}",
      "curveMode": 1,
      "curveTo": "{0.87349634815121846, 0.49996407333416554}",
      "hasCurveFrom": false,
      "hasCurveTo": false,
      "point": "{0.87349634815121846, 0.49996407333416554}"
    },
    {
      "_class": "curvePoint",
      "cornerRadius": 0,
      "curveFrom": "{1.0035879565580736, 0.69815536191206495}",
      "curveMode": 4,
      "curveTo": "{0.98820726569336204, 0.675051398676348}",
      "hasCurveFrom": true,
      "hasCurveTo": false,
      "point": "{0.98820726569336204, 0.675051398676348}"
    },
    {
      "_class": "curvePoint",
      "cornerRadius": 0,
      "curveFrom": "{0.97436002498246088, 0.77422667226529363}",
      "curveMode": 2,
      "curveTo": "{1.0039474785005382, 0.72709985146529832}",
      "hasCurveFrom": true,
      "hasCurveTo": true,
      "point": "{0.98914463784896656, 0.7505176091095499}"
    },
    {
      "_class": "curvePoint",
      "cornerRadius": 0,
      "curveFrom": "{0.91696698186739289, 0.78882242804155389}",
      "curveMode": 4,
      "curveTo": "{0.9468029934159029, 0.78885124118631833}",
      "hasCurveFrom": false,
      "hasCurveTo": true,
      "point": "{0.91696698186739289, 0.78882242804155389}"
    },
    {
      "_class": "curvePoint",
      "cornerRadius": 0,
      "curveFrom": "{0.68469397314314073, 0.78882242804155389}",
      "curveMode": 1,
      "curveTo": "{0.68469397314314073, 0.78882242804155389}",
      "hasCurveFrom": false,
      "hasCurveTo": false,
      "point": "{0.68469397314314073, 0.78882242804155389}"
    },
    {
      "_class": "curvePoint",
      "cornerRadius": 0,
      "curveFrom": "{0.55611366417232844, 0.98581832702222683}",
      "curveMode": 4,
      "curveTo": "{0.5709204277566019, 0.9628377901673556}",
      "hasCurveFrom": true,
      "hasCurveTo": false,
      "point": "{0.5709204277566019, 0.9628377901673556}"
    },
    {
      "_class": "curvePoint",
      "cornerRadius": 0,
      "curveFrom": "{0.47112947585724385, 1.0001228601369185}",
      "curveMode": 2,
      "curveTo": "{0.52915080625799693, 0.99994504384446625}",
      "hasCurveFrom": true,
      "hasCurveTo": true,
      "point": "{0.49999260131583478, 0.99999918166855362}"
    },
    {
      "_class": "curvePoint",
      "cornerRadius": 0,
      "curveFrom": "{0.42968968964547116, 0.96348096809718409}",
      "curveMode": 4,
      "curveTo": "{0.44436405234630261, 0.98621980222825512}",
      "hasCurveFrom": false,
      "hasCurveTo": true,
      "point": "{0.42968968964547116, 0.96348096809718409}"
    },
    {
      "_class": "curvePoint",
      "cornerRadius": 0,
      "curveFrom": "{0.3154474581811299, 0.78882242804155389}",
      "curveMode": 1,
      "curveTo": "{0.3154474581811299, 0.78882242804155389}",
      "hasCurveFrom": false,
      "hasCurveTo": false,
      "point": "{0.3154474581811299, 0.78882242804155389}"
    },
    {
      "_class": "curvePoint",
      "cornerRadius": 0,
      "curveFrom": "{0.05331832669076892, 0.78884273515902414}",
      "curveMode": 4,
      "curveTo": "{0.083057277937427246, 0.78882242804155389}",
      "hasCurveFrom": true,
      "hasCurveTo": false,
      "point": "{0.083057277937427246, 0.78882242804155389}"
    },
    {
      "_class": "curvePoint",
      "cornerRadius": 0,
      "curveFrom": "{-0.0034106323891824174, 0.72684693822812307}",
      "curveMode": 2,
      "curveTo": "{0.025871900671814163, 0.77420979253124844}",
      "hasCurveFrom": true,
      "hasCurveTo": true,
      "point": "{0.011230634141315816, 0.75052836537968581}"
    },
    {
      "_class": "curvePoint",
      "cornerRadius": 0,
      "curveFrom": "{0.012363794535561523, 0.6744796849609449}",
      "curveMode": 4,
      "curveTo": "{-0.0029776286835303412, 0.69778718587665489}",
      "hasCurveFrom": false,
      "hasCurveTo": true,
      "point": "{0.012363794535561523, 0.6744796849609449}"
    },
    {
      "_class": "curvePoint",
      "cornerRadius": 0,
      "curveFrom": "{0.12644979730730233, 0.49996407333416554}",
      "curveMode": 1,
      "curveTo": "{0.12644979730730233, 0.49996407333416554}",
      "hasCurveFrom": false,
      "hasCurveTo": false,
      "point": "{0.12644979730730233, 0.49996407333416554}"
    },
    {
      "_class": "curvePoint",
      "cornerRadius": 0,
      "curveFrom": "{-0.0035975957218612339, 0.30175516422895804}",
      "curveMode": 4,
      "curveTo": "{0.011777936938308801, 0.32487674799198307}",
      "hasCurveFrom": true,
      "hasCurveTo": false,
      "point": "{0.011777936938308801, 0.32487674799198307}"
    }
  ],
  "resizingConstraint": 63,
  "resizingType": 0,
  "rotation": 0,
  "shouldBreakMaskChain": false,
  "style": {
    "_class": "style",
    "blur": {
      "_class": "blur",
      "center": "{0.5, 0.5}",
      "isEnabled": false,
      "motionAngle": 0,
      "radius": 10,
      "saturation": 1,
      "type": 0
    },
    "borderOptions": {
      "_class": "borderOptions",
      "dashPattern": [
      ],
      "isEnabled": true,
      "lineCapStyle": 0,
      "lineJoinStyle": 0
    },
    "borders": [
    ],
    "colorControls": {
      "_class": "colorControls",
      "brightness": 0,
      "contrast": 1,
      "hue": 0,
      "isEnabled": false,
      "saturation": 1
    },
    "contextSettings": {
      "_class": "graphicsContextSettings",
      "blendMode": 0,
      "opacity": 1
    },
    "do_objectID": "96301323-3570-4860-A889-3D5F3D693794",
    "endMarkerType": 0,
    "fills": [
    ],
    "innerShadows": [
    ],
    "miterLimit": 10,
    "shadows": [
    ],
    "startMarkerType": 0,
    "windingRule": 1
  }
}