{
  "_class": "group",
  "booleanOperation": -1,
  "clippingMaskMode": 0,
  "do_objectID": "52894D82-97E9-47A0-8EB2-82510B8E5852",
  "exportOptions": {
    "_class": "exportOptions",
    "exportFormats": [
    ],
    "includedLayerIds": [
    ],
    "layerOptions": 0,
    "shouldTrim": false
  },
  "frame": {
    "_class": "rect",
    "constrainProportions": false,
    "height": 100,
    "width": 874,
    "x": 790,
    "y": 225.5669958345502
  },
  "groupLayout": {
    "_class": "MSImmutableFreeformGroupLayout"
  },
  "hasClickThrough": false,
  "hasClippingMask": false,
  "isFixedToViewport": false,
  "isFlippedHorizontal": false,
  "isFlippedVertical": false,
  "isLocked": false,
  "isVisible": true,
  "layerListExpandedType": 2,
  "layers": [
    {
      "class": "rectangle",
      "id": "A29A06F6-D54A-40D6-8170-5AC75ADB126A"
    },
    {
      "class": "rectangle",
      "id": "F5701A90-172F-4988-AB15-87ED924E18C0"
    },
    {
      "class": "rectangle",
      "id": "1DB8C8D2-D109-4C2C-AAF9-4C495485C21D"
    },
    {
      "class": "rectangle",
      "id": "624EEA83-3748-4A4F-A9D5-ECC49252FFBB"
    },
    {
      "class": "rectangle",
      "id": "006B0878-CC0D-40AF-B495-839252CED238"
    },
    {
      "class": "rectangle",
      "id": "20C1A409-8F30-4996-8F2E-064EAC9E7826"
    },
    {
      "class": "rectangle",
      "id": "AD58858F-207E-4658-8CCC-807F6691D9FF"
    },
    {
      "class": "rectangle",
      "id": "87C2C319-AF6F-43E3-AE1D-D35C76075D7B"
    },
    {
      "class": "rectangle",
      "id": "ECF7BCF1-1407-4B3B-AAF4-A4D130E31225"
    },
    {
      "class": "rectangle",
      "id": "49BD04BD-37E5-4378-9BFA-15B0B10A7F99"
    },
    {
      "class": "rectangle",
      "id": "7E985836-17C0-45C7-B963-5543085B6A05"
    },
    {
      "class": "rectangle",
      "id": "3646F195-C9FC-40E5-911D-35E692442D9D"
    },
    {
      "class": "rectangle",
      "id": "F0DD3DBB-BCD2-42F9-BBE1-31578672D803"
    },
    {
      "class": "rectangle",
      "id": "244347BD-4BB3-40F7-AE3E-5FB108928986"
    },
    {
      "class": "rectangle",
      "id": "B5B701DD-2191-4084-94DC-CE8E4F55922A"
    },
    {
      "class": "text",
      "id": "ADDA7D8C-186D-4EDC-BDF2-9149B3629B04"
    }
  ],
  "name": "gray",
  "nameIsFixed": true,
  "resizingConstraint": 63,
  "resizingType": 0,
  "rotation": 0,
  "shouldBreakMaskChain": false,
  "style": {
    "_class": "style",
    "blur": {
      "_class": "blur",
      "center": "{0.5, 0.5}",
      "isEnabled": false,
      "motionAngle": 0,
      "radius": 10,
      "saturation": 1,
      "type": 0
    },
    "borderOptions": {
      "_class": "borderOptions",
      "dashPattern": [
      ],
      "isEnabled": true,
      "lineCapStyle": 0,
      "lineJoinStyle": 0
    },
    "borders": [
    ],
    "colorControls": {
      "_class": "colorControls",
      "brightness": 0,
      "contrast": 1,
      "hue": 0,
      "isEnabled": false,
      "saturation": 1
    },
    "contextSettings": {
      "_class": "graphicsContextSettings",
      "blendMode": 0,
      "opacity": 1
    },
    "do_objectID": "AB03F462-189C-4244-BA8F-049B67C96175",
    "endMarkerType": 0,
    "fills": [
    ],
    "innerShadows": [
    ],
    "miterLimit": 10,
    "shadows": [
    ],
    "startMarkerType": 0,
    "windingRule": 1
  }
}