{
  "_class": "shapePath",
  "booleanOperation": -1,
  "clippingMaskMode": 0,
  "do_objectID": "4D17A7FE-E34D-40D5-94F1-024FECB461C8",
  "edited": true,
  "exportOptions": {
    "_class": "exportOptions",
    "exportFormats": [
    ],
    "includedLayerIds": [
    ],
    "layerOptions": 0,
    "shouldTrim": false
  },
  "frame": {
    "_class": "rect",
    "constrainProportions": false,
    "height": 13.94081839978429,
    "width": 7.9060078454417,
    "x": 8.593992173308301,
    "y": 5.029580390480123
  },
  "hasClippingMask": false,
  "isClosed": true,
  "isFixedToViewport": false,
  "isFlippedHorizontal": false,
  "isFlippedVertical": false,
  "isLocked": false,
  "isVisible": true,
  "layerListExpandedType": 1,
  "name": "caret-left",
  "nameIsFixed": false,
  "pointRadiusBehaviour": 1,
  "points": [
    {
      "_class": "curvePoint",
      "cornerRadius": 0,
      "curveFrom": "{1, 0.067384016307472747}",
      "curveMode": 4,
      "curveTo": "{1, 0.0074722715642084698}",
      "hasCurveFrom": false,
      "hasCurveTo": true,
      "point": "{1, 0.067384016307472747}"
    },
    {
      "_class": "curvePoint",
      "cornerRadius": 0,
      "curveFrom": "{1, 0.99252922183846504}",
      "curveMode": 4,
      "curveTo": "{1, 0.93261747709520082}",
      "hasCurveFrom": true,
      "hasCurveTo": false,
      "point": "{1, 0.93261747709520082}"
    },
    {
      "_class": "curvePoint",
      "cornerRadius": 0,
      "curveFrom": "{0.79757087420662098, 0.98016893596596333}",
      "curveMode": 4,
      "curveTo": "{0.87227079090367388, 1.022532168204171}",
      "hasCurveFrom": false,
      "hasCurveTo": true,
      "point": "{0.79757087420662098, 0.98016893596596333}"
    },
    {
      "_class": "curvePoint",
      "cornerRadius": 0,
      "curveFrom": "{-0.011576441570838637, 0.52129164173525466}",
      "curveMode": 4,
      "curveTo": "{0.034729324712515885, 0.54755220557209916}",
      "hasCurveFrom": true,
      "hasCurveTo": false,
      "point": "{0.034729324712515885, 0.54755220557209916}"
    },
    {
      "_class": "curvePoint",
      "cornerRadius": 0,
      "curveFrom": "{0.034729324712515885, 0.45244928783057448}",
      "curveMode": 4,
      "curveTo": "{-0.011576441570838637, 0.47870985166741892}",
      "hasCurveFrom": false,
      "hasCurveTo": true,
      "point": "{0.034729324712515885, 0.45244928783057448}"
    },
    {
      "_class": "curvePoint",
      "cornerRadius": 0,
      "curveFrom": "{0.87227079090367388, -0.0225340372296455}",
      "curveMode": 4,
      "curveTo": "{0.79757087420662098, 0.019832557436710412}",
      "hasCurveFrom": true,
      "hasCurveTo": false,
      "point": "{0.79757087420662098, 0.019832557436710412}"
    }
  ],
  "resizingConstraint": 63,
  "resizingType": 0,
  "rotation": 0,
  "sharedStyleID": "6384751B-1CEA-4B08-9A1E-01F42BC9555A",
  "shouldBreakMaskChain": false,
  "style": {
    "_class": "style",
    "blur": {
      "_class": "blur",
      "center": "{0.5, 0.5}",
      "isEnabled": false,
      "motionAngle": 0,
      "radius": 10,
      "saturation": 1,
      "type": 0
    },
    "borderOptions": {
      "_class": "borderOptions",
      "dashPattern": [
      ],
      "isEnabled": true,
      "lineCapStyle": 0,
      "lineJoinStyle": 9223372036854776000
    },
    "borders": [
    ],
    "colorControls": {
      "_class": "colorControls",
      "brightness": 0,
      "contrast": 1,
      "hue": 0,
      "isEnabled": false,
      "saturation": 1
    },
    "contextSettings": {
      "_class": "graphicsContextSettings",
      "blendMode": 0,
      "opacity": 1
    },
    "do_objectID": "31C1FABA-149A-4D68-9BD9-33DEB27F9F06",
    "endMarkerType": 0,
    "fills": [
      {
        "_class": "fill",
        "color": {
          "_class": "color",
          "alpha": 1,
          "blue": 0,
          "green": 0,
          "red": 0
        },
        "contextSettings": {
          "_class": "graphicsContextSettings",
          "blendMode": 0,
          "opacity": 1
        },
        "fillType": 0,
        "gradient": {
          "_class": "gradient",
          "elipseLength": 0,
          "from": "{0.5, 0}",
          "gradientType": 0,
          "stops": [
            {
              "_class": "gradientStop",
              "color": {
                "_class": "color",
                "alpha": 1,
                "blue": 1,
                "green": 1,
                "red": 1
              },
              "position": 0
            },
            {
              "_class": "gradientStop",
              "color": {
                "_class": "color",
                "alpha": 1,
                "blue": 0,
                "green": 0,
                "red": 0
              },
              "position": 1
            }
          ],
          "to": "{0.5, 1}"
        },
        "isEnabled": true,
        "noiseIndex": 0,
        "noiseIntensity": 0,
        "patternFillType": 1,
        "patternTileScale": 1
      }
    ],
    "innerShadows": [
    ],
    "miterLimit": 10,
    "shadows": [
    ],
    "startMarkerType": 0,
    "windingRule": 1
  }
}